nightcore/__init__.py
nightcore/aio.py
nightcore/change.py
nightcore/cli.py
nightcore/effect.py
nightcore-1.1.0.dist-info/entry_points.txt
nightcore-1.1.0.dist-info/LICENSE
nightcore-1.1.0.dist-info/WHEEL
nightcore-1.1.0.dist-info/METADATA
nightcore-1.1.0.dist-info/RECORD
