Metadata-Version: 2.1
Name: nightcore
Version: 1.1.0
Summary: Intuitive CLI and API for modifying the speed/pitch of audio
Home-page: https://github.com/SeparateRecords/nightcore
License: MIT
Keywords: nightcore,cli,audio,pitch,speed
Author: SeparateRecords
Author-email: me@rob.ac
Requires-Python: >=3.7,<4.0
Classifier: Development Status :: 5 - Production/Stable
Classifier: Environment :: Console
Classifier: License :: OSI Approved :: MIT License
Classifier: Programming Language :: Python :: 3
Classifier: Programming Language :: Python :: 3.7
Classifier: Programming Language :: Python :: Implementation :: CPython
Classifier: Topic :: Multimedia :: Sound/Audio
Classifier: Topic :: Multimedia :: Sound/Audio :: Conversion
Requires-Dist: click (>=7.0,<8.0)
Requires-Dist: pydub (>=0.23.1,<0.24.0)
